[{"MatchID":2119985538,"Lane":"MIDDLE","Role":"DUO_CARRY","Kills":9,"Deaths":7,"Assists":9,"GoldEarned":18414,"Winner":true,"GameDuration":2729},{"MatchID":2120002240,"Lane":"BOTTOM","Role":"DUO_CARRY","Kills":6,"Deaths":1,"Assists":6,"GoldEarned":9737,"Winner":true,"GameDuration":1218},{"MatchID":2120051072,"Lane":"TOP","Role":"SOLO","Kills":5,"Deaths":1,"Assists":7,"GoldEarned":9035,"Winner":true,"GameDuration":1327},{"MatchID":2120064772,"Lane":"BOTTOM","Role":"DUO_CARRY","Kills":4,"Deaths":2,"Assists":2,"GoldEarned":9306,"Winner":true,"GameDuration":1322},{"MatchID":2120657692,"Lane":"BOTTOM","Role":"DUO_CARRY","Kills":7,"Deaths":8,"Assists":4,"GoldEarned":12876,"Winner":false,"GameDuration":2022},{"MatchID":2120662999,"Lane":"BOTTOM","Role":"DUO_CARRY","Kills":8,"Deaths":1,"Assists":13,"GoldEarned":16826,"Winner":true,"GameDuration":2232},{"MatchID":2120711820,"Lane":"TOP","Role":"SOLO","Kills":8,"Deaths":1,"Assists":7,"GoldEarned":12633,"Winner":false,"GameDuration":1785},{"MatchID":2120725941,"Lane":"BOTTOM","Role":"DUO_CARRY","Kills":4,"Deaths":6,"Assists":6,"GoldEarned":8263,"Winner":false,"GameDuration":1444},{"MatchID":2120764858,"Lane":"BOTTOM","Role":"DUO_CARRY","Kills":8,"Deaths":2,"Assists":7,"GoldEarned":11779,"Winner":true,"GameDuration":1454},{"MatchID":2120780684,"Lane":"TOP","Role":"SOLO","Kills":5,"Deaths":2,"Assists":8,"GoldEarned":8853,"Winner":true,"GameDuration":1257},{"MatchID":2121560501,"Lane":"TOP","Role":"SOLO","Kills":10,"Deaths":6,"Assists":16,"GoldEarned":19063,"Winner":true,"GameDuration":2797},{"MatchID":2121564541,"Lane":"TOP","Role":"SOLO","Kills":10,"Deaths":5,"Assists":4,"GoldEarned":13915,"Winner":true,"GameDuration":1993},{"MatchID":2121588857,"Lane":"BOTTOM","Role":"DUO_CARRY","Kills":6,"Deaths":6,"Assists":3,"GoldEarned":12283,"Winner":false,"GameDuration":1981},{"MatchID":2121591942,"Lane":"MIDDLE","Role":"SOLO","Kills":6,"Deaths":1,"Assists":6,"GoldEarned":9871,"Winner":true,"GameDuration":1496},{"MatchID":2121651311,"Lane":"TOP","Role":"SOLO","Kills":11,"Deaths":2,"Assists":13,"GoldEarned":14652,"Winner":true,"GameDuration":2100},{"MatchID":2121658706,"Lane":"BOTTOM","Role":"DUO_CARRY","Kills":13,"Deaths":2,"Assists":6,"GoldEarned":11599,"Winner":true,"GameDuration":1424},{"MatchID":2121682612,"Lane":"BOTTOM","Role":"DUO_CARRY","Kills":8,"Deaths":3,"Assists":13,"GoldEarned":13983,"Winner":true,"GameDuration":1881},{"MatchID":2121696514,"Lane":"BOTTOM","Role":"DUO","Kills":1,"Deaths":5,"Assists":1,"GoldEarned":6553,"Winner":false,"GameDuration":1344},{"MatchID":2121709594,"Lane":"BOTTOM","Role":"DUO_CARRY","Kills":9,"Deaths":1,"Assists":7,"GoldEarned":10289,"Winner":true,"GameDuration":1256},{"MatchID":2121747350,"Lane":"BOTTOM","Role":"DUO_CARRY","Kills":11,"Deaths":2,"Assists":12,"GoldEarned":17343,"Winner":true,"GameDuration":2176},{"MatchID":2121763000,"Lane":"BOTTOM","Role":"DUO_CARRY","Kills":4,"Deaths":2,"Assists":3,"GoldEarned":8007,"Winner":true,"GameDuration":1229},{"MatchID":2122478617,"Lane":"TOP","Role":"SOLO","Kills":10,"Deaths":8,"Assists":4,"GoldEarned":14932,"Winner":true,"GameDuration":2077},{"MatchID":2122685976,"Lane":"TOP","Role":"SOLO","Kills":12,"Deaths":4,"Assists":12,"GoldEarned":14256,"Winner":true,"GameDuration":1807},{"MatchID":2122711911,"Lane":"TOP","Role":"SOLO","Kills":6,"Deaths":4,"Assists":8,"GoldEarned":11977,"Winner":true,"GameDuration":1792},{"MatchID":2122749738,"Lane":"TOP","Role":"SOLO","Kills":6,"Deaths":8,"Assists":4,"GoldEarned":11356,"Winner":false,"GameDuration":1955},{"MatchID":2122773368,"Lane":"TOP","Role":"SOLO","Kills":4,"Deaths":7,"Assists":7,"GoldEarned":14756,"Winner":true,"GameDuration":2202},{"MatchID":2122805427,"Lane":"BOTTOM","Role":"DUO_CARRY","Kills":6,"Deaths":6,"Assists":16,"GoldEarned":13486,"Winner":true,"GameDuration":2031},{"MatchID":2122875106,"Lane":"TOP","Role":"SOLO","Kills":7,"Deaths":1,"Assists":7,"GoldEarned":11955,"Winner":true,"GameDuration":1625},{"MatchID":2122879805,"Lane":"BOTTOM","Role":"DUO_CARRY","Kills":4,"Deaths":7,"Assists":7,"GoldEarned":11328,"Winner":false,"GameDuration":1860},{"MatchID":2122919794,"Lane":"BOTTOM","Role":"DUO_CARRY","Kills":10,"Deaths":4,"Assists":4,"GoldEarned":11463,"Winner":true,"GameDuration":1441},{"MatchID":2123593365,"Lane":"BOTTOM","Role":"DUO_CARRY","Kills":19,"Deaths":5,"Assists":9,"GoldEarned":24699,"Winner":true,"GameDuration":3006},{"MatchID":2123599279,"Lane":"TOP","Role":"SOLO","Kills":12,"Deaths":9,"Assists":15,"GoldEarned":18106,"Winner":false,"GameDuration":2920},{"MatchID":2123599946,"Lane":"BOTTOM","Role":"DUO_CARRY","Kills":7,"Deaths":5,"Assists":4,"GoldEarned":13806,"Winner":false,"GameDuration":2074},{"MatchID":2123715100,"Lane":"BOTTOM","Role":"DUO_CARRY","Kills":7,"Deaths":7,"Assists":6,"GoldEarned":13418,"Winner":true,"GameDuration":2029},{"MatchID":2123878498,"Lane":"TOP","Role":"SOLO","Kills":3,"Deaths":4,"Assists":8,"GoldEarned":10574,"Winner":false,"GameDuration":1794},{"MatchID":2124043931,"Lane":"BOTTOM","Role":"DUO_CARRY","Kills":4,"Deaths":4,"Assists":3,"GoldEarned":16088,"Winner":false,"GameDuration":2776},{"MatchID":2124088810,"Lane":"TOP","Role":"SOLO","Kills":4,"Deaths":1,"Assists":1,"GoldEarned":11049,"Winner":true,"GameDuration":1659},{"MatchID":2124102067,"Lane":"BOTTOM","Role":"DUO_CARRY","Kills":15,"Deaths":5,"Assists":13,"GoldEarned":16197,"Winner":true,"GameDuration":1957},{"MatchID":2124144256,"Lane":"BOTTOM","Role":"DUO_CARRY","Kills":6,"Deaths":2,"Assists":9,"GoldEarned":11449,"Winner":true,"GameDuration":1420},{"MatchID":2124807754,"Lane":"TOP","Role":"SOLO","Kills":3,"Deaths":0,"Assists":2,"GoldEarned":5476,"Winner":true,"GameDuration":790},{"MatchID":2124821530,"Lane":"TOP","Role":"SOLO","Kills":8,"Deaths":2,"Assists":12,"GoldEarned":17325,"Winner":true,"GameDuration":2262},{"MatchID":2124860452,"Lane":"BOTTOM","Role":"DUO_CARRY","Kills":7,"Deaths":5,"Assists":4,"GoldEarned":15574,"Winner":false,"GameDuration":2494},{"MatchID":2124875942,"Lane":"TOP","Role":"SOLO","Kills":8,"Deaths":0,"Assists":8,"GoldEarned":9791,"Winner":true,"GameDuration":1250},{"MatchID":2124939777,"Lane":"BOTTOM","Role":"DUO_CARRY","Kills":14,"Deaths":6,"Assists":5,"GoldEarned":16158,"Winner":true,"GameDuration":2095},{"MatchID":2125841317,"Lane":"MIDDLE","Role":"SOLO","Kills":3,"Deaths":1,"Assists":8,"GoldEarned":8655,"Winner":true,"GameDuration":1322},{"MatchID":2125845538,"Lane":"TOP","Role":"SOLO","Kills":4,"Deaths":0,"Assists":4,"GoldEarned":6516,"Winner":true,"GameDuration":940},{"MatchID":2125867746,"Lane":"BOTTOM","Role":"DUO_CARRY","Kills":2,"Deaths":1,"Assists":2,"GoldEarned":7845,"Winner":true,"GameDuration":1129},{"MatchID":2125907499,"Lane":"TOP","Role":"SOLO","Kills":10,"Deaths":1,"Assists":1,"GoldEarned":11288,"Winner":true,"GameDuration":1407},{"MatchID":2125921690,"Lane":"TOP","Role":"SOLO","Kills":5,"Deaths":6,"Assists":9,"GoldEarned":10170,"Winner":true,"GameDuration":1496},{"MatchID":2126889373,"Lane":"TOP","Role":"SOLO","Kills":2,"Deaths":7,"Assists":9,"GoldEarned":10127,"Winner":false,"GameDuration":1720},{"MatchID":2126895729,"Lane":"TOP","Role":"SOLO","Kills":7,"Deaths":2,"Assists":11,"GoldEarned":12316,"Winner":true,"GameDuration":1787},{"MatchID":2126933943,"Lane":"JUNGLE","Role":"NONE","Kills":7,"Deaths":5,"Assists":6,"GoldEarned":9698,"Winner":false,"GameDuration":1723},{"MatchID":2126957386,"Lane":"TOP","Role":"SOLO","Kills":8,"Deaths":6,"Assists":8,"GoldEarned":18244,"Winner":true,"GameDuration":2789},{"MatchID":2127014082,"Lane":"BOTTOM","Role":"DUO_CARRY","Kills":12,"Deaths":4,"Assists":9,"GoldEarned":15033,"Winner":true,"GameDuration":1959},{"MatchID":2127055279,"Lane":"TOP","Role":"SOLO","Kills":1,"Deaths":2,"Assists":5,"GoldEarned":7971,"Winner":true,"GameDuration":1215},{"MatchID":2127060012,"Lane":"TOP","Role":"SOLO","Kills":7,"Deaths":1,"Assists":7,"GoldEarned":10398,"Winner":true,"GameDuration":1453},{"MatchID":2127695026,"Lane":"BOTTOM","Role":"DUO_CARRY","Kills":11,"Deaths":3,"Assists":9,"GoldEarned":11267,"Winner":true,"GameDuration":1489},{"MatchID":2127717487,"Lane":"TOP","Role":"SOLO","Kills":6,"Deaths":10,"Assists":13,"GoldEarned":14722,"Winner":true,"GameDuration":2483},{"MatchID":2127768451,"Lane":"TOP","Role":"SOLO","Kills":1,"Deaths":9,"Assists":11,"GoldEarned":8596,"Winner":false,"GameDuration":1674},{"MatchID":2127773325,"Lane":"BOTTOM","Role":"DUO_CARRY","Kills":6,"Deaths":7,"Assists":3,"GoldEarned":10958,"Winner":true,"GameDuration":1721},{"MatchID":2127838888,"Lane":"BOTTOM","Role":"DUO_CARRY","Kills":2,"Deaths":3,"Assists":3,"GoldEarned":10897,"Winner":true,"GameDuration":1587},{"MatchID":2127842337,"Lane":"BOTTOM","Role":"SOLO","Kills":6,"Deaths":8,"Assists":9,"GoldEarned":15376,"Winner":false,"GameDuration":2306},{"MatchID":2127903812,"Lane":"TOP","Role":"SOLO","Kills":6,"Deaths":3,"Assists":5,"GoldEarned":15744,"Winner":true,"GameDuration":2409},{"MatchID":2128675074,"Lane":"BOTTOM","Role":"DUO_CARRY","Kills":6,"Deaths":6,"Assists":9,"GoldEarned":14063,"Winner":false,"GameDuration":2341},{"MatchID":2128688065,"Lane":"TOP","Role":"SOLO","Kills":4,"Deaths":2,"Assists":9,"GoldEarned":14542,"Winner":true,"GameDuration":2182},{"MatchID":2128696330,"Lane":"BOTTOM","Role":"DUO_CARRY","Kills":4,"Deaths":0,"Assists":11,"GoldEarned":11219,"Winner":true,"GameDuration":1497},{"MatchID":2128741123,"Lane":"TOP","Role":"SOLO","Kills":6,"Deaths":2,"Assists":3,"GoldEarned":9643,"Winner":true,"GameDuration":1193},{"MatchID":2128752738,"Lane":"BOTTOM","Role":"DUO_CARRY","Kills":1,"Deaths":8,"Assists":11,"GoldEarned":11699,"Winner":false,"GameDuration":1890},{"MatchID":2128807696,"Lane":"TOP","Role":"SOLO","Kills":2,"Deaths":5,"Assists":0,"GoldEarned":6328,"Winner":false,"GameDuration":1141},{"MatchID":2128809793,"Lane":"BOTTOM","Role":"DUO_CARRY","Kills":8,"Deaths":14,"Assists":8,"GoldEarned":11380,"Winner":false,"GameDuration":1907},{"MatchID":2128813390,"Lane":"TOP","Role":"SOLO","Kills":5,"Deaths":3,"Assists":3,"GoldEarned":12314,"Winner":true,"GameDuration":1845},{"MatchID":2128855178,"Lane":"TOP","Role":"SOLO","Kills":3,"Deaths":0,"Assists":3,"GoldEarned":11481,"Winner":true,"GameDuration":1448},{"MatchID":2128870420,"Lane":"BOTTOM","Role":"DUO_CARRY","Kills":7,"Deaths":1,"Assists":9,"GoldEarned":12449,"Winner":true,"GameDuration":1738},{"MatchID":2128878764,"Lane":"TOP","Role":"SOLO","Kills":11,"Deaths":3,"Assists":8,"GoldEarned":12358,"Winner":true,"GameDuration":1555},{"MatchID":2128924872,"Lane":"TOP","Role":"SOLO","Kills":6,"Deaths":5,"Assists":2,"GoldEarned":8403,"Winner":true,"GameDuration":1219},{"MatchID":2129937913,"Lane":"BOTTOM","Role":"DUO_CARRY","Kills":5,"Deaths":7,"Assists":9,"GoldEarned":11845,"Winner":false,"GameDuration":1876},{"MatchID":2129978061,"Lane":"BOTTOM","Role":"DUO_CARRY","Kills":8,"Deaths":4,"Assists":4,"GoldEarned":12449,"Winner":false,"GameDuration":1721},{"MatchID":2129993099,"Lane":"TOP","Role":"SOLO","Kills":1,"Deaths":3,"Assists":1,"GoldEarned":7758,"Winner":false,"GameDuration":1386},{"MatchID":2130027340,"Lane":"BOTTOM","Role":"DUO_CARRY","Kills":6,"Deaths":1,"Assists":6,"GoldEarned":9378,"Winner":true,"GameDuration":1249},{"MatchID":2130032890,"Lane":"BOTTOM","Role":"DUO_CARRY","Kills":2,"Deaths":8,"Assists":3,"GoldEarned":6884,"Winner":false,"GameDuration":1321},{"MatchID":2130081471,"Lane":"BOTTOM","Role":"DUO_CARRY","Kills":12,"Deaths":6,"Assists":9,"GoldEarned":17412,"Winner":true,"GameDuration":2159},{"MatchID":2130088289,"Lane":"TOP","Role":"SOLO","Kills":3,"Deaths":5,"Assists":4,"GoldEarned":10268,"Winner":true,"GameDuration":1586},{"MatchID":2130144000,"Lane":"TOP","Role":"SOLO","Kills":5,"Deaths":1,"Assists":2,"GoldEarned":9357,"Winner":true,"GameDuration":1177},{"MatchID":2130167924,"Lane":"TOP","Role":"SOLO","Kills":8,"Deaths":2,"Assists":3,"GoldEarned":12781,"Winner":true,"GameDuration":1817},{"MatchID":2131212037,"Lane":"TOP","Role":"SOLO","Kills":3,"Deaths":9,"Assists":4,"GoldEarned":11835,"Winner":false,"GameDuration":2037},{"MatchID":2131218090,"Lane":"TOP","Role":"SOLO","Kills":5,"Deaths":1,"Assists":3,"GoldEarned":10846,"Winner":true,"GameDuration":1518},{"MatchID":2131259257,"Lane":"TOP","Role":"SOLO","Kills":5,"Deaths":2,"Assists":4,"GoldEarned":10427,"Winner":true,"GameDuration":1702},{"MatchID":2131272783,"Lane":"TOP","Role":"SOLO","Kills":7,"Deaths":3,"Assists":9,"GoldEarned":11819,"Winner":true,"GameDuration":1741},{"MatchID":2131333798,"Lane":"TOP","Role":"SOLO","Kills":10,"Deaths":5,"Assists":18,"GoldEarned":14959,"Winner":false,"GameDuration":2362},{"MatchID":2131371919,"Lane":"TOP","Role":"SOLO","Kills":4,"Deaths":9,"Assists":21,"GoldEarned":14671,"Winner":true,"GameDuration":2590},{"MatchID":2131422351,"Lane":"TOP","Role":"SOLO","Kills":5,"Deaths":5,"Assists":6,"GoldEarned":10004,"Winner":true,"GameDuration":1423},{"MatchID":2132564052,"Lane":"BOTTOM","Role":"DUO_CARRY","Kills":11,"Deaths":4,"Assists":9,"GoldEarned":13623,"Winner":true,"GameDuration":1848},{"MatchID":2132690212,"Lane":"TOP","Role":"SOLO","Kills":1,"Deaths":3,"Assists":4,"GoldEarned":8404,"Winner":true,"GameDuration":1396},{"MatchID":2133094814,"Lane":"TOP","Role":"SOLO","Kills":1,"Deaths":3,"Assists":0,"GoldEarned":5925,"Winner":false,"GameDuration":1269},{"MatchID":2133106332,"Lane":"TOP","Role":"SOLO","Kills":3,"Deaths":6,"Assists":3,"GoldEarned":8126,"Winner":false,"GameDuration":1477},{"MatchID":2133165725,"Lane":"TOP","Role":"SOLO","Kills":12,"Deaths":5,"Assists":9,"GoldEarned":13225,"Winner":true,"GameDuration":1878},{"MatchID":2133171382,"Lane":"TOP","Role":"SOLO","Kills":5,"Deaths":2,"Assists":14,"GoldEarned":10904,"Winner":true,"GameDuration":1499},{"MatchID":2133232415,"Lane":"BOTTOM","Role":"DUO_CARRY","Kills":5,"Deaths":5,"Assists":3,"GoldEarned":9223,"Winner":false,"GameDuration":1620},{"MatchID":2133237092,"Lane":"TOP","Role":"SOLO","Kills":6,"Deaths":2,"Assists":9,"GoldEarned":11985,"Winner":true,"GameDuration":1789},{"MatchID":2133292803,"Lane":"TOP","Role":"SOLO","Kills":5,"Deaths":7,"Assists":9,"GoldEarned":14271,"Winner":false,"GameDuration":2469},{"MatchID":2134407819,"Lane":"TOP","Role":"SOLO","Kills":3,"Deaths":4,"Assists":18,"GoldEarned":12082,"Winner":true,"GameDuration":2194},{"MatchID":2134414684,"Lane":"BOTTOM","Role":"DUO_CARRY","Kills":5,"Deaths":3,"Assists":7,"GoldEarned":11312,"Winner":true,"GameDuration":1623},{"MatchID":2134472402,"Lane":"BOTTOM","Role":"DUO_CARRY","Kills":4,"Deaths":5,"Assists":10,"GoldEarned":11940,"Winner":false,"GameDuration":1970},{"MatchID":2134497883,"Lane":"BOTTOM","Role":"DUO_CARRY","Kills":0,"Deaths":6,"Assists":1,"GoldEarned":5911,"Winner":false,"GameDuration":1218},{"MatchID":2134521762,"Lane":"BOTTOM","Role":"DUO_CARRY","Kills":3,"Deaths":3,"Assists":1,"GoldEarned":7373,"Winner":false,"GameDuration":1237},{"MatchID":2134526999,"Lane":"BOTTOM","Role":"SOLO","Kills":1,"Deaths":0,"Assists":7,"GoldEarned":6715,"Winner":true,"GameDuration":1243},{"MatchID":2134918127,"Lane":"TOP","Role":"SOLO","Kills":1,"Deaths":0,"Assists":0,"GoldEarned":2698,"Winner":true,"GameDuration":472},{"MatchID":2134939881,"Lane":"TOP","Role":"SOLO","Kills":8,"Deaths":4,"Assists":7,"GoldEarned":12583,"Winner":false,"GameDuration":1964},{"MatchID":2134977524,"Lane":"BOTTOM","Role":"DUO_CARRY","Kills":6,"Deaths":1,"Assists":7,"GoldEarned":10365,"Winner":true,"GameDuration":1422},{"MatchID":2134981199,"Lane":"TOP","Role":"SOLO","Kills":5,"Deaths":2,"Assists":9,"GoldEarned":10808,"Winner":true,"GameDuration":1470},{"MatchID":2135033019,"Lane":"BOTTOM","Role":"DUO_CARRY","Kills":2,"Deaths":0,"Assists":3,"GoldEarned":8386,"Winner":true,"GameDuration":1233},{"MatchID":2135345270,"Lane":"BOTTOM","Role":"DUO_CARRY","Kills":2,"Deaths":10,"Assists":4,"GoldEarned":9089,"Winner":false,"GameDuration":1651},{"MatchID":2135357260,"Lane":"TOP","Role":"SOLO","Kills":9,"Deaths":6,"Assists":8,"GoldEarned":16417,"Winner":false,"GameDuration":2527},{"MatchID":2135363017,"Lane":"TOP","Role":"SOLO","Kills":6,"Deaths":2,"Assists":10,"GoldEarned":13111,"Winner":true,"GameDuration":1883},{"MatchID":2135410213,"Lane":"BOTTOM","Role":"DUO_CARRY","Kills":8,"Deaths":5,"Assists":2,"GoldEarned":14135,"Winner":false,"GameDuration":2059},{"MatchID":2135413560,"Lane":"BOTTOM","Role":"DUO_CARRY","Kills":7,"Deaths":6,"Assists":6,"GoldEarned":15606,"Winner":true,"GameDuration":2278},{"MatchID":2135496103,"Lane":"TOP","Role":"SOLO","Kills":8,"Deaths":5,"Assists":9,"GoldEarned":17010,"Winner":false,"GameDuration":2483},{"MatchID":2135541912,"Lane":"TOP","Role":"SOLO","Kills":2,"Deaths":5,"Assists":13,"GoldEarned":11298,"Winner":true,"GameDuration":1996},{"MatchID":2135556872,"Lane":"MIDDLE","Role":"SOLO","Kills":7,"Deaths":4,"Assists":6,"GoldEarned":10505,"Winner":true,"GameDuration":1688},{"MatchID":2135611507,"Lane":"BOTTOM","Role":"DUO_CARRY","Kills":9,"Deaths":1,"Assists":8,"GoldEarned":15810,"Winner":true,"GameDuration":2085},{"MatchID":2135617928,"Lane":"BOTTOM","Role":"DUO_CARRY","Kills":6,"Deaths":6,"Assists":1,"GoldEarned":10335,"Winner":false,"GameDuration":1695},{"MatchID":2136567933,"Lane":"TOP","Role":"SOLO","Kills":1,"Deaths":5,"Assists":5,"GoldEarned":9832,"Winner":false,"GameDuration":1798},{"MatchID":2136574479,"Lane":"BOTTOM","Role":"DUO_CARRY","Kills":5,"Deaths":4,"Assists":6,"GoldEarned":9702,"Winner":false,"GameDuration":1603},{"MatchID":2136625849,"Lane":"BOTTOM","Role":"DUO_CARRY","Kills":7,"Deaths":1,"Assists":7,"GoldEarned":17315,"Winner":true,"GameDuration":2455},{"MatchID":2136631219,"Lane":"TOP","Role":"SOLO","Kills":5,"Deaths":4,"Assists":11,"GoldEarned":11174,"Winner":true,"GameDuration":1562},{"MatchID":2136691980,"Lane":"TOP","Role":"SOLO","Kills":6,"Deaths":3,"Assists":5,"GoldEarned":13700,"Winner":true,"GameDuration":1742},{"MatchID":2136732103,"Lane":"TOP","Role":"SOLO","Kills":1,"Deaths":5,"Assists":4,"GoldEarned":8155,"Winner":false,"GameDuration":1671},{"MatchID":2136737331,"Lane":"BOTTOM","Role":"DUO_CARRY","Kills":10,"Deaths":6,"Assists":14,"GoldEarned":15610,"Winner":true,"GameDuration":1880},{"MatchID":2136833028,"Lane":"BOTTOM","Role":"DUO_CARRY","Kills":5,"Deaths":4,"Assists":11,"GoldEarned":13517,"Winner":true,"GameDuration":1876},{"MatchID":2136838835,"Lane":"BOTTOM","Role":"DUO_CARRY","Kills":4,"Deaths":6,"Assists":6,"GoldEarned":8377,"Winner":false,"GameDuration":1593},{"MatchID":2137125102,"Lane":"TOP","Role":"SOLO","Kills":12,"Deaths":5,"Assists":15,"GoldEarned":16187,"Winner":true,"GameDuration":2213},{"MatchID":2137201610,"Lane":"BOTTOM","Role":"DUO_SUPPORT","Kills":1,"Deaths":7,"Assists":9,"GoldEarned":8536,"Winner":false,"GameDuration":1857},{"MatchID":2137267175,"Lane":"BOTTOM","Role":"DUO_CARRY","Kills":12,"Deaths":4,"Assists":6,"GoldEarned":15543,"Winner":true,"GameDuration":1925},{"MatchID":2137272928,"Lane":"TOP","Role":"SOLO","Kills":5,"Deaths":1,"Assists":4,"GoldEarned":8006,"Winner":true,"GameDuration":987},{"MatchID":2137314351,"Lane":"TOP","Role":"SOLO","Kills":7,"Deaths":3,"Assists":11,"GoldEarned":11794,"Winner":true,"GameDuration":1702},{"MatchID":2137825034,"Lane":"MIDDLE","Role":"SOLO","Kills":10,"Deaths":5,"Assists":6,"GoldEarned":11474,"Winner":true,"GameDuration":1467},{"MatchID":2137870898,"Lane":"TOP","Role":"SOLO","Kills":2,"Deaths":5,"Assists":2,"GoldEarned":8145,"Winner":false,"GameDuration":1479},{"MatchID":2137874213,"Lane":"BOTTOM","Role":"DUO_CARRY","Kills":4,"Deaths":8,"Assists":8,"GoldEarned":13221,"Winner":false,"GameDuration":2148},{"MatchID":2137950902,"Lane":"BOTTOM","Role":"DUO_CARRY","Kills":3,"Deaths":2,"Assists":8,"GoldEarned":8704,"Winner":true,"GameDuration":1269},{"MatchID":2137996736,"Lane":"BOTTOM","Role":"DUO_CARRY","Kills":4,"Deaths":6,"Assists":6,"GoldEarned":12684,"Winner":true,"GameDuration":1774},{"MatchID":2138000940,"Lane":"TOP","Role":"SOLO","Kills":10,"Deaths":0,"Assists":2,"GoldEarned":9656,"Winner":true,"GameDuration":1219},{"MatchID":2138052220,"Lane":"MIDDLE","Role":"SOLO","Kills":6,"Deaths":12,"Assists":9,"GoldEarned":11168,"Winner":false,"GameDuration":1989},{"MatchID":2138140456,"Lane":"TOP","Role":"SOLO","Kills":2,"Deaths":2,"Assists":2,"GoldEarned":8378,"Winner":true,"GameDuration":1271},{"MatchID":2138164760,"Lane":"BOTTOM","Role":"DUO_CARRY","Kills":6,"Deaths":5,"Assists":12,"GoldEarned":12681,"Winner":true,"GameDuration":1955},{"MatchID":2138391522,"Lane":"TOP","Role":"SOLO","Kills":10,"Deaths":1,"Assists":4,"GoldEarned":8932,"Winner":true,"GameDuration":1284},{"MatchID":2138525621,"Lane":"BOTTOM","Role":"DUO_CARRY","Kills":2,"Deaths":10,"Assists":2,"GoldEarned":10082,"Winner":false,"GameDuration":1934},{"MatchID":2138562781,"Lane":"TOP","Role":"SOLO","Kills":4,"Deaths":4,"Assists":1,"GoldEarned":6775,"Winner":false,"GameDuration":1171},{"MatchID":2138567680,"Lane":"TOP","Role":"SOLO","Kills":3,"Deaths":7,"Assists":8,"GoldEarned":10038,"Winner":false,"GameDuration":1820},{"MatchID":2138643503,"Lane":"TOP","Role":"SOLO","Kills":1,"Deaths":5,"Assists":5,"GoldEarned":12077,"Winner":false,"GameDuration":2317},{"MatchID":2138697908,"Lane":"TOP","Role":"SOLO","Kills":6,"Deaths":7,"Assists":11,"GoldEarned":14388,"Winner":true,"GameDuration":2418},{"MatchID":2138757258,"Lane":"TOP","Role":"SOLO","Kills":3,"Deaths":3,"Assists":6,"GoldEarned":8428,"Winner":false,"GameDuration":1519},{"MatchID":2138826206,"Lane":"TOP","Role":"SOLO","Kills":6,"Deaths":2,"Assists":4,"GoldEarned":14125,"Winner":true,"GameDuration":1802},{"MatchID":2140205270,"Lane":"TOP","Role":"SOLO","Kills":4,"Deaths":2,"Assists":5,"GoldEarned":12024,"Winner":true,"GameDuration":1728},{"MatchID":2140227924,"Lane":"BOTTOM","Role":"DUO_CARRY","Kills":7,"Deaths":3,"Assists":1,"GoldEarned":13410,"Winner":true,"GameDuration":1859},{"MatchID":2140236048,"Lane":"TOP","Role":"SOLO","Kills":4,"Deaths":5,"Assists":12,"GoldEarned":11098,"Winner":true,"GameDuration":1654},{"MatchID":2140300354,"Lane":"TOP","Role":"SOLO","Kills":4,"Deaths":2,"Assists":13,"GoldEarned":13603,"Winner":true,"GameDuration":2058},{"MatchID":2140304144,"Lane":"BOTTOM","Role":"DUO_CARRY","Kills":20,"Deaths":8,"Assists":13,"GoldEarned":16939,"Winner":false,"GameDuration":2174},{"MatchID":2140354332,"Lane":"BOTTOM","Role":"DUO_CARRY","Kills":5,"Deaths":5,"Assists":5,"GoldEarned":12065,"Winner":true,"GameDuration":1766},{"MatchID":2140358752,"Lane":"TOP","Role":"SOLO","Kills":0,"Deaths":3,"Assists":6,"GoldEarned":7160,"Winner":false,"GameDuration":1381},{"MatchID":2140402880,"Lane":"BOTTOM","Role":"DUO_CARRY","Kills":7,"Deaths":10,"Assists":13,"GoldEarned":16080,"Winner":false,"GameDuration":2502},{"MatchID":2140451166,"Lane":"BOTTOM","Role":"DUO_CARRY","Kills":11,"Deaths":3,"Assists":8,"GoldEarned":22170,"Winner":true,"GameDuration":3136},{"MatchID":2140469388,"Lane":"BOTTOM","Role":"DUO_CARRY","Kills":8,"Deaths":4,"Assists":9,"GoldEarned":11771,"Winner":true,"GameDuration":1680},{"MatchID":2140525436,"Lane":"BOTTOM","Role":"DUO_CARRY","Kills":2,"Deaths":9,"Assists":0,"GoldEarned":6836,"Winner":false,"GameDuration":1466},{"MatchID":2140622567,"Lane":"TOP","Role":"SOLO","Kills":6,"Deaths":9,"Assists":8,"GoldEarned":13340,"Winner":true,"GameDuration":2272},{"MatchID":2140690724,"Lane":"TOP","Role":"SOLO","Kills":3,"Deaths":4,"Assists":11,"GoldEarned":9842,"Winner":true,"GameDuration":1514},{"MatchID":2140707549,"Lane":"TOP","Role":"SOLO","Kills":10,"Deaths":3,"Assists":5,"GoldEarned":12587,"Winner":true,"GameDuration":1666},{"MatchID":2141469030,"Lane":"BOTTOM","Role":"SOLO","Kills":6,"Deaths":5,"Assists":9,"GoldEarned":12243,"Winner":false,"GameDuration":1897},{"MatchID":2141524141,"Lane":"TOP","Role":"SOLO","Kills":2,"Deaths":4,"Assists":3,"GoldEarned":8272,"Winner":false,"GameDuration":1485},{"MatchID":2141528745,"Lane":"BOTTOM","Role":"DUO_CARRY","Kills":10,"Deaths":1,"Assists":3,"GoldEarned":16755,"Winner":true,"GameDuration":2021},{"MatchID":2141586227,"Lane":"BOTTOM","Role":"DUO_CARRY","Kills":3,"Deaths":8,"Assists":5,"GoldEarned":10059,"Winner":false,"GameDuration":1784},{"MatchID":2141612910,"Lane":"BOTTOM","Role":"DUO_CARRY","Kills":15,"Deaths":6,"Assists":5,"GoldEarned":15650,"Winner":false,"GameDuration":1960},{"MatchID":2141674259,"Lane":"BOTTOM","Role":"DUO_CARRY","Kills":3,"Deaths":3,"Assists":2,"GoldEarned":7259,"Winner":false,"GameDuration":1213},{"MatchID":2141688876,"Lane":"BOTTOM","Role":"DUO_CARRY","Kills":7,"Deaths":6,"Assists":5,"GoldEarned":13631,"Winner":false,"GameDuration":2027},{"MatchID":2141756290,"Lane":"BOTTOM","Role":"DUO_CARRY","Kills":5,"Deaths":7,"Assists":3,"GoldEarned":12077,"Winner":false,"GameDuration":1985},{"MatchID":2141804749,"Lane":"TOP","Role":"SOLO","Kills":4,"Deaths":0,"Assists":6,"GoldEarned":9095,"Winner":true,"GameDuration":1284},{"MatchID":2142213975,"Lane":"BOTTOM","Role":"DUO_CARRY","Kills":7,"Deaths":1,"Assists":9,"GoldEarned":12589,"Winner":true,"GameDuration":1435},{"MatchID":2142217811,"Lane":"TOP","Role":"SOLO","Kills":5,"Deaths":4,"Assists":7,"GoldEarned":9449,"Winner":true,"GameDuration":1286},{"MatchID":2142285354,"Lane":"BOTTOM","Role":"DUO_CARRY","Kills":9,"Deaths":11,"Assists":6,"GoldEarned":14300,"Winner":false,"GameDuration":2202},{"MatchID":2142290710,"Lane":"BOTTOM","Role":"DUO_CARRY","Kills":4,"Deaths":3,"Assists":0,"GoldEarned":6902,"Winner":false,"GameDuration":1094},{"MatchID":2142366549,"Lane":"BOTTOM","Role":"DUO_CARRY","Kills":6,"Deaths":8,"Assists":13,"GoldEarned":11079,"Winner":false,"GameDuration":1610},{"MatchID":2142371035,"Lane":"BOTTOM","Role":"DUO_CARRY","Kills":12,"Deaths":4,"Assists":8,"GoldEarned":15679,"Winner":false,"GameDuration":2120},{"MatchID":2142551100,"Lane":"TOP","Role":"SOLO","Kills":5,"Deaths":1,"Assists":3,"GoldEarned":9923,"Winner":true,"GameDuration":1212},{"MatchID":2142686262,"Lane":"TOP","Role":"SOLO","Kills":6,"Deaths":5,"Assists":16,"GoldEarned":10383,"Winner":true,"GameDuration":1511},{"MatchID":2142691437,"Lane":"TOP","Role":"SOLO","Kills":3,"Deaths":3,"Assists":6,"GoldEarned":8227,"Winner":true,"GameDuration":1304},{"MatchID":2142772294,"Lane":"TOP","Role":"SOLO","Kills":3,"Deaths":3,"Assists":5,"GoldEarned":12194,"Winner":true,"GameDuration":1937},{"MatchID":2142829993,"Lane":"TOP","Role":"SOLO","Kills":8,"Deaths":2,"Assists":7,"GoldEarned":13229,"Winner":true,"GameDuration":1656},{"MatchID":2143212862,"Lane":"TOP","Role":"SOLO","Kills":8,"Deaths":2,"Assists":1,"GoldEarned":11262,"Winner":true,"GameDuration":1647},{"MatchID":2143234600,"Lane":"TOP","Role":"SOLO","Kills":2,"Deaths":5,"Assists":12,"GoldEarned":11387,"Winner":false,"GameDuration":2174},{"MatchID":2143238096,"Lane":"BOTTOM","Role":"SOLO","Kills":1,"Deaths":3,"Assists":2,"GoldEarned":7629,"Winner":false,"GameDuration":1528},{"MatchID":2143267370,"Lane":"TOP","Role":"SOLO","Kills":1,"Deaths":8,"Assists":14,"GoldEarned":11915,"Winner":true,"GameDuration":2026},{"MatchID":2143272848,"Lane":"BOTTOM","Role":"DUO_CARRY","Kills":3,"Deaths":5,"Assists":5,"GoldEarned":11681,"Winner":true,"GameDuration":1946},{"MatchID":2143317211,"Lane":"BOTTOM","Role":"DUO_SUPPORT","Kills":1,"Deaths":4,"Assists":16,"GoldEarned":9617,"Winner":true,"GameDuration":1609},{"MatchID":2143341596,"Lane":"BOTTOM","Role":"DUO_CARRY","Kills":8,"Deaths":5,"Assists":7,"GoldEarned":14222,"Winner":false,"GameDuration":1996},{"MatchID":2143375032,"Lane":"BOTTOM","Role":"DUO_CARRY","Kills":4,"Deaths":4,"Assists":3,"GoldEarned":10960,"Winner":false,"GameDuration":1966},{"MatchID":2143430620,"Lane":"BOTTOM","Role":"DUO_CARRY","Kills":0,"Deaths":5,"Assists":3,"GoldEarned":6442,"Winner":false,"GameDuration":1221},{"MatchID":2143496925,"Lane":"TOP","Role":"SOLO","Kills":0,"Deaths":7,"Assists":0,"GoldEarned":5488,"Winner":false,"GameDuration":1236},{"MatchID":2143558287,"Lane":"BOTTOM","Role":"DUO_CARRY","Kills":2,"Deaths":10,"Assists":5,"GoldEarned":8304,"Winner":false,"GameDuration":1554},{"MatchID":2143570903,"Lane":"TOP","Role":"SOLO","Kills":5,"Deaths":4,"Assists":8,"GoldEarned":10393,"Winner":false,"GameDuration":1636},{"MatchID":2143634276,"Lane":"BOTTOM","Role":"DUO_CARRY","Kills":2,"Deaths":10,"Assists":7,"GoldEarned":13177,"Winner":false,"GameDuration":2363},{"MatchID":2144253241,"Lane":"TOP","Role":"SOLO","Kills":2,"Deaths":5,"Assists":3,"GoldEarned":6295,"Winner":false,"GameDuration":1216},{"MatchID":2144269384,"Lane":"TOP","Role":"SOLO","Kills":8,"Deaths":2,"Assists":12,"GoldEarned":16901,"Winner":false,"GameDuration":2940},{"MatchID":2144275109,"Lane":"BOTTOM","Role":"DUO_CARRY","Kills":9,"Deaths":1,"Assists":7,"GoldEarned":12873,"Winner":true,"GameDuration":1528},{"MatchID":2144277388,"Lane":"TOP","Role":"SOLO","Kills":5,"Deaths":0,"Assists":0,"GoldEarned":7778,"Winner":true,"GameDuration":969},{"MatchID":2144338459,"Lane":"TOP","Role":"SOLO","Kills":1,"Deaths":11,"Assists":14,"GoldEarned":12431,"Winner":true,"GameDuration":2018},{"MatchID":2144393487,"Lane":"TOP","Role":"SOLO","Kills":2,"Deaths":4,"Assists":1,"GoldEarned":8305,"Winner":false,"GameDuration":1360},{"MatchID":2144408199,"Lane":"BOTTOM","Role":"DUO_CARRY","Kills":8,"Deaths":7,"Assists":6,"GoldEarned":12562,"Winner":false,"GameDuration":1728},{"MatchID":2144458799,"Lane":"BOTTOM","Role":"DUO_CARRY","Kills":9,"Deaths":3,"Assists":10,"GoldEarned":15454,"Winner":false,"GameDuration":1986},{"MatchID":2144462753,"Lane":"TOP","Role":"SOLO","Kills":2,"Deaths":4,"Assists":10,"GoldEarned":10892,"Winner":false,"GameDuration":2058},{"MatchID":2144524528,"Lane":"TOP","Role":"SOLO","Kills":5,"Deaths":6,"Assists":5,"GoldEarned":11822,"Winner":false,"GameDuration":2127},{"MatchID":2144568766,"Lane":"TOP","Role":"SOLO","Kills":6,"Deaths":4,"Assists":8,"GoldEarned":11189,"Winner":true,"GameDuration":1581},{"MatchID":2144634111,"Lane":"TOP","Role":"SOLO","Kills":1,"Deaths":5,"Assists":8,"GoldEarned":8792,"Winner":false,"GameDuration":1765},{"MatchID":2144690330,"Lane":"BOTTOM","Role":"DUO_CARRY","Kills":9,"Deaths":10,"Assists":10,"GoldEarned":14562,"Winner":false,"GameDuration":2321},{"MatchID":2144709624,"Lane":"BOTTOM","Role":"DUO_CARRY","Kills":4,"Deaths":2,"Assists":9,"GoldEarned":11499,"Winner":true,"GameDuration":1656},{"MatchID":2145372968,"Lane":"TOP","Role":"SOLO","Kills":5,"Deaths":3,"Assists":5,"GoldEarned":11542,"Winner":false,"GameDuration":2126},{"MatchID":2145379597,"Lane":"TOP","Role":"SOLO","Kills":5,"Deaths":6,"Assists":15,"GoldEarned":16383,"Winner":true,"GameDuration":2256},{"MatchID":2145395478,"Lane":"BOTTOM","Role":"DUO_CARRY","Kills":5,"Deaths":4,"Assists":0,"GoldEarned":13380,"Winner":false,"GameDuration":2048},{"MatchID":2145483322,"Lane":"TOP","Role":"SOLO","Kills":3,"Deaths":8,"Assists":19,"GoldEarned":13002,"Winner":true,"GameDuration":2328},{"MatchID":2145539322,"Lane":"TOP","Role":"SOLO","Kills":9,"Deaths":2,"Assists":11,"GoldEarned":9831,"Winner":true,"GameDuration":1238},{"MatchID":2145543714,"Lane":"TOP","Role":"SOLO","Kills":12,"Deaths":6,"Assists":5,"GoldEarned":15081,"Winner":false,"GameDuration":2114},{"MatchID":2145602640,"Lane":"BOTTOM","Role":"DUO_CARRY","Kills":8,"Deaths":3,"Assists":10,"GoldEarned":11934,"Winner":true,"GameDuration":1845},{"MatchID":2145607836,"Lane":"TOP","Role":"SOLO","Kills":6,"Deaths":4,"Assists":11,"GoldEarned":14183,"Winner":true,"GameDuration":1826},{"MatchID":2145649118,"Lane":"BOTTOM","Role":"DUO_CARRY","Kills":6,"Deaths":6,"Assists":6,"GoldEarned":14414,"Winner":false,"GameDuration":2154},{"MatchID":2145653267,"Lane":"BOTTOM","Role":"DUO_CARRY","Kills":2,"Deaths":5,"Assists":3,"GoldEarned":13235,"Winner":true,"GameDuration":2029},{"MatchID":2145724764,"Lane":"TOP","Role":"SOLO","Kills":2,"Deaths":5,"Assists":13,"GoldEarned":12953,"Winner":true,"GameDuration":1997},{"MatchID":2145821173,"Lane":"BOTTOM","Role":"DUO_CARRY","Kills":4,"Deaths":10,"Assists":4,"GoldEarned":10189,"Winner":false,"GameDuration":1828},{"MatchID":2145827503,"Lane":"TOP","Role":"SOLO","Kills":7,"Deaths":6,"Assists":12,"GoldEarned":17041,"Winner":false,"GameDuration":2704},{"MatchID":2145907257,"Lane":"TOP","Role":"SOLO","Kills":3,"Deaths":0,"Assists":2,"GoldEarned":9100,"Winner":true,"GameDuration":1254},{"MatchID":2146010369,"Lane":"BOTTOM","Role":"DUO_CARRY","Kills":14,"Deaths":2,"Assists":5,"GoldEarned":12156,"Winner":true,"GameDuration":1310},{"MatchID":2146026793,"Lane":"TOP","Role":"SOLO","Kills":4,"Deaths":1,"Assists":9,"GoldEarned":9956,"Winner":true,"GameDuration":1387},{"MatchID":2146082631,"Lane":"TOP","Role":"SOLO","Kills":6,"Deaths":9,"Assists":4,"GoldEarned":14100,"Winner":false,"GameDuration":2108},{"MatchID":2146140886,"Lane":"BOTTOM","Role":"DUO_CARRY","Kills":10,"Deaths":6,"Assists":11,"GoldEarned":14722,"Winner":true,"GameDuration":2054},{"MatchID":2146333796,"Lane":"TOP","Role":"SOLO","Kills":3,"Deaths":4,"Assists":11,"GoldEarned":11369,"Winner":true,"GameDuration":1788},{"MatchID":2146337940,"Lane":"TOP","Role":"SOLO","Kills":4,"Deaths":3,"Assists":6,"GoldEarned":9212,"Winner":true,"GameDuration":1368},{"MatchID":2146354718,"Lane":"TOP","Role":"SOLO","Kills":4,"Deaths":10,"Assists":11,"GoldEarned":16685,"Winner":false,"GameDuration":2898},{"MatchID":2146429972,"Lane":"TOP","Role":"SOLO","Kills":2,"Deaths":1,"Assists":3,"GoldEarned":5825,"Winner":true,"GameDuration":903},{"MatchID":2146441833,"Lane":"TOP","Role":"SOLO","Kills":8,"Deaths":9,"Assists":9,"GoldEarned":13578,"Winner":true,"GameDuration":2185},{"MatchID":2146825580,"Lane":"BOTTOM","Role":"DUO_CARRY","Kills":1,"Deaths":3,"Assists":3,"GoldEarned":11627,"Winner":true,"GameDuration":1862},{"MatchID":2146850731,"Lane":"BOTTOM","Role":"DUO_CARRY","Kills":5,"Deaths":0,"Assists":9,"GoldEarned":9264,"Winner":true,"GameDuration":1241},{"MatchID":2146881351,"Lane":"TOP","Role":"SOLO","Kills":3,"Deaths":0,"Assists":5,"GoldEarned":7490,"Winner":true,"GameDuration":1249},{"MatchID":2146915661,"Lane":"BOTTOM","Role":"DUO_CARRY","Kills":5,"Deaths":3,"Assists":4,"GoldEarned":11584,"Winner":true,"GameDuration":1662},{"MatchID":2146942377,"Lane":"BOTTOM","Role":"DUO_CARRY","Kills":7,"Deaths":7,"Assists":6,"GoldEarned":13569,"Winner":false,"GameDuration":2078},{"MatchID":2147013180,"Lane":"BOTTOM","Role":"DUO_CARRY","Kills":5,"Deaths":11,"Assists":7,"GoldEarned":11784,"Winner":false,"GameDuration":2158},{"MatchID":2147041391,"Lane":"BOTTOM","Role":"DUO_CARRY","Kills":2,"Deaths":3,"Assists":4,"GoldEarned":8625,"Winner":false,"GameDuration":1727},{"MatchID":2147109749,"Lane":"TOP","Role":"SOLO","Kills":4,"Deaths":2,"Assists":11,"GoldEarned":11031,"Winner":true,"GameDuration":1659},{"MatchID":2147125591,"Lane":"TOP","Role":"SOLO","Kills":0,"Deaths":6,"Assists":3,"GoldEarned":8093,"Winner":false,"GameDuration":1664},{"MatchID":2147164517,"Lane":"BOTTOM","Role":"DUO_CARRY","Kills":2,"Deaths":7,"Assists":2,"GoldEarned":6431,"Winner":false,"GameDuration":1216},{"MatchID":2147179537,"Lane":"TOP","Role":"SOLO","Kills":0,"Deaths":6,"Assists":1,"GoldEarned":4007,"Winner":false,"GameDuration":1023},{"MatchID":2147596098,"Lane":"TOP","Role":"SOLO","Kills":4,"Deaths":3,"Assists":10,"GoldEarned":12005,"Winner":true,"GameDuration":1715},{"MatchID":2147646118,"Lane":"TOP","Role":"SOLO","Kills":4,"Deaths":5,"Assists":5,"GoldEarned":10120,"Winner":false,"GameDuration":1753},{"MatchID":2147650362,"Lane":"TOP","Role":"SOLO","Kills":2,"Deaths":5,"Assists":13,"GoldEarned":11847,"Winner":true,"GameDuration":1968},{"MatchID":2147696352,"Lane":"TOP","Role":"SOLO","Kills":3,"Deaths":7,"Assists":7,"GoldEarned":10074,"Winner":false,"GameDuration":1629},{"MatchID":2147700758,"Lane":"TOP","Role":"SOLO","Kills":4,"Deaths":2,"Assists":9,"GoldEarned":9820,"Winner":true,"GameDuration":1519},{"MatchID":2147798553,"Lane":"BOTTOM","Role":"DUO_CARRY","Kills":1,"Deaths":3,"Assists":6,"GoldEarned":10742,"Winner":true,"GameDuration":1547},{"MatchID":2147801044,"Lane":"BOTTOM","Role":"DUO_CARRY","Kills":6,"Deaths":4,"Assists":16,"GoldEarned":14653,"Winner":true,"GameDuration":2132},{"MatchID":2147864393,"Lane":"TOP","Role":"SOLO","Kills":0,"Deaths":2,"Assists":4,"GoldEarned":7868,"Winner":true,"GameDuration":1244},{"MatchID":2148009773,"Lane":"BOTTOM","Role":"DUO_CARRY","Kills":1,"Deaths":1,"Assists":9,"GoldEarned":7705,"Winner":true,"GameDuration":1370},{"MatchID":2148029092,"Lane":"TOP","Role":"SOLO","Kills":1,"Deaths":4,"Assists":7,"GoldEarned":9380,"Winner":false,"GameDuration":1554},{"MatchID":2148188407,"Lane":"BOTTOM","Role":"DUO_CARRY","Kills":3,"Deaths":8,"Assists":5,"GoldEarned":11798,"Winner":false,"GameDuration":1980},{"MatchID":2148276693,"Lane":"TOP","Role":"SOLO","Kills":3,"Deaths":5,"Assists":1,"GoldEarned":8292,"Winner":false,"GameDuration":1579},{"MatchID":2148468502,"Lane":"BOTTOM","Role":"DUO_CARRY","Kills":1,"Deaths":7,"Assists":4,"GoldEarned":8429,"Winner":false,"GameDuration":1757},{"MatchID":2148518678,"Lane":"TOP","Role":"SOLO","Kills":8,"Deaths":4,"Assists":11,"GoldEarned":13995,"Winner":true,"GameDuration":2028},{"MatchID":2148520240,"Lane":"BOTTOM","Role":"DUO_CARRY","Kills":0,"Deaths":4,"Assists":4,"GoldEarned":5205,"Winner":false,"GameDuration":1104},{"MatchID":2148524405,"Lane":"TOP","Role":"SOLO","Kills":5,"Deaths":2,"Assists":6,"GoldEarned":13266,"Winner":true,"GameDuration":1739},{"MatchID":2148571515,"Lane":"BOTTOM","Role":"DUO_CARRY","Kills":4,"Deaths":0,"Assists":7,"GoldEarned":9025,"Winner":true,"GameDuration":1212},{"MatchID":2148576324,"Lane":"BOTTOM","Role":"DUO_CARRY","Kills":9,"Deaths":2,"Assists":6,"GoldEarned":13342,"Winner":true,"GameDuration":1612},{"MatchID":2148645191,"Lane":"TOP","Role":"SOLO","Kills":0,"Deaths":4,"Assists":9,"GoldEarned":12246,"Winner":true,"GameDuration":2029},{"MatchID":2148649928,"Lane":"BOTTOM","Role":"DUO_CARRY","Kills":1,"Deaths":4,"Assists":1,"GoldEarned":11512,"Winner":false,"GameDuration":1948},{"MatchID":2148659633,"Lane":"TOP","Role":"SOLO","Kills":4,"Deaths":9,"Assists":7,"GoldEarned":10975,"Winner":true,"GameDuration":1838},{"MatchID":2149747279,"Lane":"TOP","Role":"SOLO","Kills":3,"Deaths":1,"Assists":6,"GoldEarned":9342,"Winner":true,"GameDuration":1414},{"MatchID":2149823868,"Lane":"TOP","Role":"SOLO","Kills":3,"Deaths":0,"Assists":2,"GoldEarned":8897,"Winner":true,"GameDuration":1213},{"MatchID":2151309297,"Lane":"TOP","Role":"SOLO","Kills":4,"Deaths":3,"Assists":16,"GoldEarned":13015,"Winner":true,"GameDuration":1849},{"MatchID":2151325338,"Lane":"BOTTOM","Role":"DUO_CARRY","Kills":8,"Deaths":10,"Assists":3,"GoldEarned":12033,"Winner":false,"GameDuration":1941},{"MatchID":2151375675,"Lane":"TOP","Role":"SOLO","Kills":11,"Deaths":4,"Assists":5,"GoldEarned":10218,"Winner":true,"GameDuration":1400},{"MatchID":2151381757,"Lane":"BOTTOM","Role":"DUO_CARRY","Kills":8,"Deaths":3,"Assists":4,"GoldEarned":9758,"Winner":true,"GameDuration":1332},{"MatchID":2154716712,"Lane":"TOP","Role":"SOLO","Kills":5,"Deaths":5,"Assists":12,"GoldEarned":12914,"Winner":true,"GameDuration":2132},{"MatchID":2154733317,"Lane":"BOTTOM","Role":"DUO_CARRY","Kills":9,"Deaths":3,"Assists":9,"GoldEarned":13326,"Winner":true,"GameDuration":1682},{"MatchID":2154737885,"Lane":"TOP","Role":"SOLO","Kills":5,"Deaths":6,"Assists":3,"GoldEarned":9719,"Winner":false,"GameDuration":1650},{"MatchID":2156749698,"Lane":"BOTTOM","Role":"DUO_CARRY","Kills":7,"Deaths":3,"Assists":6,"GoldEarned":14011,"Winner":true,"GameDuration":1906},{"MatchID":2156958039,"Lane":"BOTTOM","Role":"DUO_CARRY","Kills":2,"Deaths":4,"Assists":2,"GoldEarned":8310,"Winner":false,"GameDuration":1411},{"MatchID":2157416187,"Lane":"TOP","Role":"SOLO","Kills":1,"Deaths":5,"Assists":9,"GoldEarned":7394,"Winner":true,"GameDuration":1475},{"MatchID":2157423598,"Lane":"BOTTOM","Role":"DUO_CARRY","Kills":4,"Deaths":5,"Assists":10,"GoldEarned":12128,"Winner":true,"GameDuration":1788},{"MatchID":2157427570,"Lane":"BOTTOM","Role":"DUO_CARRY","Kills":10,"Deaths":9,"Assists":16,"GoldEarned":18721,"Winner":true,"GameDuration":2631},{"MatchID":2157464931,"Lane":"BOTTOM","Role":"DUO_CARRY","Kills":7,"Deaths":1,"Assists":3,"GoldEarned":10531,"Winner":true,"GameDuration":1212},{"MatchID":2157471227,"Lane":"BOTTOM","Role":"DUO_CARRY","Kills":4,"Deaths":3,"Assists":5,"GoldEarned":8375,"Winner":true,"GameDuration":1221},{"MatchID":2157476657,"Lane":"BOTTOM","Role":"DUO_CARRY","Kills":6,"Deaths":5,"Assists":1,"GoldEarned":13179,"Winner":true,"GameDuration":1958},{"MatchID":2157608346,"Lane":"BOTTOM","Role":"DUO_CARRY","Kills":5,"Deaths":6,"Assists":7,"GoldEarned":11899,"Winner":false,"GameDuration":1902},{"MatchID":2157639289,"Lane":"TOP","Role":"SOLO","Kills":3,"Deaths":0,"Assists":3,"GoldEarned":11682,"Winner":true,"GameDuration":1573},{"MatchID":2157698589,"Lane":"TOP","Role":"SOLO","Kills":5,"Deaths":7,"Assists":9,"GoldEarned":9623,"Winner":false,"GameDuration":1637},{"MatchID":2158286268,"Lane":"TOP","Role":"SOLO","Kills":6,"Deaths":1,"Assists":4,"GoldEarned":13769,"Winner":true,"GameDuration":1963},{"MatchID":2158480108,"Lane":"TOP","Role":"SOLO","Kills":3,"Deaths":1,"Assists":6,"GoldEarned":9766,"Winner":true,"GameDuration":1421},{"MatchID":2158483992,"Lane":"TOP","Role":"SOLO","Kills":2,"Deaths":1,"Assists":6,"GoldEarned":9503,"Winner":true,"GameDuration":1509},{"MatchID":2158496713,"Lane":"TOP","Role":"SOLO","Kills":4,"Deaths":7,"Assists":11,"GoldEarned":13490,"Winner":false,"GameDuration":2677},{"MatchID":2158649115,"Lane":"TOP","Role":"SOLO","Kills":2,"Deaths":2,"Assists":1,"GoldEarned":6622,"Winner":false,"GameDuration":1189},{"MatchID":2158705790,"Lane":"TOP","Role":"SOLO","Kills":2,"Deaths":3,"Assists":6,"GoldEarned":9306,"Winner":false,"GameDuration":1691},{"MatchID":2159351294,"Lane":"TOP","Role":"SOLO","Kills":6,"Deaths":2,"Assists":16,"GoldEarned":14757,"Winner":true,"GameDuration":2305},{"MatchID":2159367518,"Lane":"BOTTOM","Role":"DUO_CARRY","Kills":5,"Deaths":6,"Assists":8,"GoldEarned":10468,"Winner":false,"GameDuration":1738},{"MatchID":2159425650,"Lane":"BOTTOM","Role":"DUO_CARRY","Kills":7,"Deaths":6,"Assists":4,"GoldEarned":11700,"Winner":false,"GameDuration":1745},{"MatchID":2159510490,"Lane":"BOTTOM","Role":"DUO_CARRY","Kills":10,"Deaths":3,"Assists":8,"GoldEarned":18825,"Winner":true,"GameDuration":2445},{"MatchID":2159528079,"Lane":"BOTTOM","Role":"DUO_CARRY","Kills":7,"Deaths":1,"Assists":6,"GoldEarned":12755,"Winner":true,"GameDuration":1654},{"MatchID":2160738628,"Lane":"BOTTOM","Role":"DUO_CARRY","Kills":2,"Deaths":6,"Assists":6,"GoldEarned":10013,"Winner":false,"GameDuration":1791},{"MatchID":2160788120,"Lane":"BOTTOM","Role":"DUO_CARRY","Kills":10,"Deaths":6,"Assists":12,"GoldEarned":17009,"Winner":true,"GameDuration":2130},{"MatchID":2160854572,"Lane":"BOTTOM","Role":"DUO_CARRY","Kills":9,"Deaths":8,"Assists":7,"GoldEarned":13030,"Winner":false,"GameDuration":2124},{"MatchID":2160902281,"Lane":"BOTTOM","Role":"DUO_CARRY","Kills":7,"Deaths":4,"Assists":3,"GoldEarned":13129,"Winner":true,"GameDuration":1856},{"MatchID":2160980070,"Lane":"TOP","Role":"SOLO","Kills":1,"Deaths":0,"Assists":3,"GoldEarned":9618,"Winner":true,"GameDuration":1405},{"MatchID":2161699440,"Lane":"MIDDLE","Role":"SOLO","Kills":5,"Deaths":4,"Assists":14,"GoldEarned":11074,"Winner":true,"GameDuration":1730},{"MatchID":2161749482,"Lane":"BOTTOM","Role":"DUO_CARRY","Kills":6,"Deaths":3,"Assists":10,"GoldEarned":13864,"Winner":true,"GameDuration":1873},{"MatchID":2161753690,"Lane":"BOTTOM","Role":"DUO_CARRY","Kills":2,"Deaths":2,"Assists":6,"GoldEarned":9738,"Winner":true,"GameDuration":1356},{"MatchID":2161814367,"Lane":"TOP","Role":"SOLO","Kills":1,"Deaths":6,"Assists":2,"GoldEarned":9216,"Winner":false,"GameDuration":1862},{"MatchID":2161880104,"Lane":"TOP","Role":"SOLO","Kills":7,"Deaths":3,"Assists":6,"GoldEarned":10984,"Winner":true,"GameDuration":1496},{"MatchID":2162277457,"Lane":"MIDDLE","Role":"SOLO","Kills":5,"Deaths":9,"Assists":3,"GoldEarned":8427,"Winner":false,"GameDuration":1492},{"MatchID":2162330120,"Lane":"BOTTOM","Role":"DUO_CARRY","Kills":5,"Deaths":3,"Assists":13,"GoldEarned":13714,"Winner":true,"GameDuration":1854},{"MatchID":2162333045,"Lane":"TOP","Role":"SOLO","Kills":1,"Deaths":4,"Assists":13,"GoldEarned":11144,"Winner":true,"GameDuration":1980},{"MatchID":2162336694,"Lane":"TOP","Role":"SOLO","Kills":4,"Deaths":9,"Assists":13,"GoldEarned":10928,"Winner":false,"GameDuration":2197},{"MatchID":2162403366,"Lane":"TOP","Role":"SOLO","Kills":10,"Deaths":5,"Assists":14,"GoldEarned":14124,"Winner":false,"GameDuration":2197},{"MatchID":2162408153,"Lane":"TOP","Role":"SOLO","Kills":5,"Deaths":3,"Assists":18,"GoldEarned":14910,"Winner":true,"GameDuration":2145},{"MatchID":2162481314,"Lane":"TOP","Role":"SOLO","Kills":4,"Deaths":2,"Assists":3,"GoldEarned":8374,"Winner":false,"GameDuration":1550},{"MatchID":2162485531,"Lane":"BOTTOM","Role":"DUO_CARRY","Kills":0,"Deaths":7,"Assists":5,"GoldEarned":6689,"Winner":false,"GameDuration":1329},{"MatchID":2162561715,"Lane":"BOTTOM","Role":"DUO_CARRY","Kills":3,"Deaths":1,"Assists":7,"GoldEarned":9493,"Winner":true,"GameDuration":1383},{"MatchID":2162651678,"Lane":"TOP","Role":"SOLO","Kills":1,"Deaths":3,"Assists":3,"GoldEarned":5345,"Winner":false,"GameDuration":1311},{"MatchID":2162812188,"Lane":"TOP","Role":"SOLO","Kills":3,"Deaths":1,"Assists":3,"GoldEarned":9089,"Winner":true,"GameDuration":1346},{"MatchID":2163636750,"Lane":"TOP","Role":"SOLO","Kills":4,"Deaths":4,"Assists":12,"GoldEarned":11405,"Winner":true,"GameDuration":1754},{"MatchID":2163669794,"Lane":"TOP","Role":"SOLO","Kills":4,"Deaths":5,"Assists":8,"GoldEarned":11524,"Winner":true,"GameDuration":1771},{"MatchID":2163673938,"Lane":"TOP","Role":"SOLO","Kills":1,"Deaths":6,"Assists":7,"GoldEarned":6375,"Winner":false,"GameDuration":1414},{"MatchID":2163707577,"Lane":"TOP","Role":"SOLO","Kills":2,"Deaths":5,"Assists":3,"GoldEarned":7942,"Winner":false,"GameDuration":1451},{"MatchID":2163754955,"Lane":"BOTTOM","Role":"DUO_CARRY","Kills":2,"Deaths":3,"Assists":2,"GoldEarned":6959,"Winner":false,"GameDuration":1234},{"MatchID":2163759169,"Lane":"BOTTOM","Role":"DUO_CARRY","Kills":1,"Deaths":6,"Assists":0,"GoldEarned":11740,"Winner":false,"GameDuration":2050},{"MatchID":2163818386,"Lane":"TOP","Role":"SOLO","Kills":3,"Deaths":5,"Assists":7,"GoldEarned":9949,"Winner":true,"GameDuration":1636},{"MatchID":2163874548,"Lane":"TOP","Role":"SOLO","Kills":4,"Deaths":7,"Assists":12,"GoldEarned":10432,"Winner":true,"GameDuration":1792},{"MatchID":2163921916,"Lane":"TOP","Role":"SOLO","Kills":4,"Deaths":7,"Assists":5,"GoldEarned":8130,"Winner":false,"GameDuration":1520},{"MatchID":2163937503,"Lane":"TOP","Role":"SOLO","Kills":3,"Deaths":8,"Assists":11,"GoldEarned":10475,"Winner":false,"GameDuration":1890},{"MatchID":2164344705,"Lane":"TOP","Role":"SOLO","Kills":4,"Deaths":1,"Assists":6,"GoldEarned":9619,"Winner":true,"GameDuration":1373},{"MatchID":2164346962,"Lane":"TOP","Role":"SOLO","Kills":5,"Deaths":5,"Assists":5,"GoldEarned":11206,"Winner":false,"GameDuration":1795},{"MatchID":2164360884,"Lane":"TOP","Role":"SOLO","Kills":3,"Deaths":4,"Assists":9,"GoldEarned":9914,"Winner":true,"GameDuration":1682},{"MatchID":2164407129,"Lane":"TOP","Role":"SOLO","Kills":0,"Deaths":5,"Assists":2,"GoldEarned":7490,"Winner":false,"GameDuration":1455},{"MatchID":2164410028,"Lane":"TOP","Role":"SOLO","Kills":4,"Deaths":8,"Assists":16,"GoldEarned":17129,"Winner":false,"GameDuration":3142},{"MatchID":2164441472,"Lane":"TOP","Role":"SOLO","Kills":5,"Deaths":3,"Assists":3,"GoldEarned":8943,"Winner":true,"GameDuration":1323},{"MatchID":2164445979,"Lane":"TOP","Role":"SOLO","Kills":4,"Deaths":6,"Assists":17,"GoldEarned":9122,"Winner":false,"GameDuration":1556},{"MatchID":2164527264,"Lane":"BOTTOM","Role":"DUO_CARRY","Kills":3,"Deaths":9,"Assists":8,"GoldEarned":11461,"Winner":false,"GameDuration":1819},{"MatchID":2164560301,"Lane":"TOP","Role":"SOLO","Kills":6,"Deaths":1,"Assists":14,"GoldEarned":12598,"Winner":true,"GameDuration":1761},{"MatchID":2164848670,"Lane":"BOTTOM","Role":"DUO_CARRY","Kills":8,"Deaths":5,"Assists":8,"GoldEarned":12626,"Winner":false,"GameDuration":2001},{"MatchID":2165356403,"Lane":"BOTTOM","Role":"DUO_CARRY","Kills":0,"Deaths":8,"Assists":7,"GoldEarned":10361,"Winner":false,"GameDuration":1900},{"MatchID":2165400440,"Lane":"BOTTOM","Role":"DUO_CARRY","Kills":3,"Deaths":7,"Assists":5,"GoldEarned":9117,"Winner":false,"GameDuration":1583},{"MatchID":2165404162,"Lane":"TOP","Role":"SOLO","Kills":2,"Deaths":4,"Assists":13,"GoldEarned":12197,"Winner":true,"GameDuration":1799},{"MatchID":2165416782,"Lane":"BOTTOM","Role":"SOLO","Kills":5,"Deaths":11,"Assists":6,"GoldEarned":13314,"Winner":true,"GameDuration":2109},{"MatchID":2165520016,"Lane":"TOP","Role":"SOLO","Kills":3,"Deaths":3,"Assists":0,"GoldEarned":8233,"Winner":false,"GameDuration":1314},{"MatchID":2165522022,"Lane":"TOP","Role":"SOLO","Kills":9,"Deaths":4,"Assists":21,"GoldEarned":14759,"Winner":true,"GameDuration":2066},{"MatchID":2165554675,"Lane":"TOP","Role":"SOLO","Kills":5,"Deaths":1,"Assists":9,"GoldEarned":7899,"Winner":true,"GameDuration":1240},{"MatchID":2165557309,"Lane":"BOTTOM","Role":"DUO_SUPPORT","Kills":1,"Deaths":6,"Assists":7,"GoldEarned":5315,"Winner":false,"GameDuration":1211},{"MatchID":2165559448,"Lane":"TOP","Role":"SOLO","Kills":3,"Deaths":4,"Assists":9,"GoldEarned":10315,"Winner":true,"GameDuration":1609},{"MatchID":2165732702,"Lane":"BOTTOM","Role":"DUO_CARRY","Kills":1,"Deaths":7,"Assists":6,"GoldEarned":9855,"Winner":false,"GameDuration":1852}]